{
    "type": "minecraft:command",
    "pools": [
        {
            "rolls": 1,
            "entries": [
                {
                    "type": "minecraft:item",
                    "name": "minecraft:jigsaw",
                    "functions": [
                        {
                            "function": "minecraft:set_nbt",
                            "tag": "{CustomModelData: 2203010, ElectrusData: {id: 'cachecol', Slot: 10b}, display: {Name: '{\"text\": \"Cachecol Kit Caloiro\", \"italic\": false, \"color\": \"#FFFFFF\"}'}}"
                        },
                        {
                            "function": "minecraft:set_lore",
                            "lore": [
                                {
                                    "text": "Proteção",
                                    "italic": false,
                                    "bold": true,
                                    "color": "#8C2D19"
                                },
                                {
                                    "text": "+6 HP",
                                    "italic": false,
                                    "color": "#FFFFFF"
                                }
                            ]
                        }
                    ]
                }
            ]
        }
    ]
}